LICENSE
MANIFEST.in
setup.py
django_representatives_votes.egg-info/PKG-INFO
django_representatives_votes.egg-info/SOURCES.txt
django_representatives_votes.egg-info/dependency_links.txt
django_representatives_votes.egg-info/entry_points.txt
django_representatives_votes.egg-info/requires.txt
django_representatives_votes.egg-info/top_level.txt
representatives_votes/__init__.py
representatives_votes/admin.py
representatives_votes/api.py
representatives_votes/models.py
representatives_votes/serializers.py
representatives_votes/contrib/__init__.py
representatives_votes/contrib/francedata/__init__.py
representatives_votes/contrib/francedata/import_dossiers.py
representatives_votes/contrib/francedata/import_scrutins.py
representatives_votes/contrib/francedata/import_votes.py
representatives_votes/contrib/francedata/tests/dossiers_expected.json
representatives_votes/contrib/francedata/tests/dossiers_input.json
representatives_votes/contrib/francedata/tests/rep_fixture.json
representatives_votes/contrib/francedata/tests/scrutins_expected.json
representatives_votes/contrib/francedata/tests/scrutins_input.json
representatives_votes/contrib/francedata/tests/test_francedata_import.py
representatives_votes/contrib/francedata/tests/votes_expected.json
representatives_votes/contrib/francedata/tests/votes_input.json
representatives_votes/contrib/parltrack/__init__.py
representatives_votes/contrib/parltrack/import_dossiers.py
representatives_votes/contrib/parltrack/import_votes.py
representatives_votes/contrib/parltrack/tests/dossiers_expected.json
representatives_votes/contrib/parltrack/tests/dossiers_fixture.json
representatives_votes/contrib/parltrack/tests/parltrack_dossier_2012-2002(INI).json
representatives_votes/contrib/parltrack/tests/single_expected.json
representatives_votes/contrib/parltrack/tests/single_fixture.json
representatives_votes/contrib/parltrack/tests/sync_expected.json
representatives_votes/contrib/parltrack/tests/sync_fixture.json
representatives_votes/contrib/parltrack/tests/test_parltrack_import.py
representatives_votes/contrib/parltrack/tests/votes_expected.json
representatives_votes/contrib/parltrack/tests/votes_fixture.json
representatives_votes/contrib/parltrack/tests/votes_initial.json
representatives_votes/fixtures/representatives_votes_test.json
