Metadata-Version: 1.1
Name: django-representatives-votes
Version: 0.0.21
Summary: Base app for government representative votes
Home-page: http://github.com/political-memory/django-representatives-votes
Author: Olivier Le Thanh Duong, Laurent Peuch, Arnaud Fabre, James Pic, Nicolas Joyard
Author-email: olivier@lethanh.be
License: GPLv3
Keywords: django government parliament votes
Platform: UNKNOWN
Classifier: Development Status :: 4 - Beta
Classifier: Environment :: Web Environment
Classifier: Framework :: Django
Classifier: Intended Audience :: Developers
Classifier: License :: OSI Approved :: GNU General Public License v3 or later (GPLv3+)
Classifier: Operating System :: OS Independent
Classifier: Programming Language :: Python :: 2
Classifier: Topic :: Software Development :: Libraries :: Python Modules
